{
  "store_name": "unknown",
  "timestamp": "2025-10-08T16:43:58.196925",
  "zones": {
    "Meeting Room": {
      "zone_name": "Meeting Room",
      "total_records": 258954,
      "categorical_mappings": {
        "A/C ON/OFF": {
          "original_values": {
            "OFF": 256074,
            "ON": 2880
          },
          "mapping": {
            "OFF": 0,
            "ON": 1
          },
          "mapped_count": 2,
          "unmapped_count": 0
        },
        "A/C Mode": {
          "original_values": {
            "COOL": 184117,
            "HEAT": 74837
          },
          "mapping": {
            "COOL": 1,
            "HEAT": 2
          },
          "mapped_count": 2,
          "unmapped_count": 0
        },
        "A/C Fan Speed": {
          "original_values": {
            "Low": 1994,
            "Medium": 633,
            "High": 253
          },
          "mapping": {
            "Low": 1,
            "Medium": 2,
            "High": 3
          },
          "mapped_count": 3,
          "unmapped_count": 0
        }
      }
    }
  }
}